PAL2
