Metadata-Version: 1.1
Name: PAL2
Version: 2015.4
Summary: PTA analysis software
Home-page: https://github.com/jellis18/PAL2
Author: Justin A. Ellis
Author-email: justin.ellis18@gmail.com
License: GPLv3
Platform: UNKNOWN
Classifier: Development Status :: 5 - Production/Stable
Classifier: Intended Audience :: Developers
Classifier: Intended Audience :: Science/Research
Classifier: License :: OSI Approved :: GNU General Public License (GPL)
Classifier: Operating System :: OS Independent
Classifier: Programming Language :: Python
